s3cd/__init__.py
s3cd/__init__.pyi
s3cd/__main__.py
s3cd/__main__.pyi
s3cd/cli.py
s3cd/cli.pyi
s3cd/info.py
s3cd/info.pyi
s3cd/operations.py
s3cd/operations.pyi
s3cd/s3.py
s3cd/s3.pyi
s3cd/settings.py
s3cd/settings.pyi
s3cd-0.0.7.dist-info/METADATA
s3cd-0.0.7.dist-info/WHEEL
s3cd-0.0.7.dist-info/entry_points.txt
s3cd-0.0.7.dist-info/top_level.txt
s3cd-0.0.7.dist-info/RECORD
