Metadata-Version: 2.4
Name: s3cd
Version: 0.0.7
Summary: S3 Content Delivery tool
Author-email: Aleksei Marusich <aleksei.marusich@rocshers.com>
License: MIT
Project-URL: Repository, https://gitlab.com/rocshers/python/s3cd
Keywords: s3,cd
Classifier: License :: OSI Approved :: MIT License
Classifier: Intended Audience :: Developers
Classifier: Intended Audience :: Information Technology
Classifier: Intended Audience :: System Administrators
Classifier: Operating System :: OS Independent
Classifier: Topic :: Software Development :: Build Tools
Classifier: Topic :: Software Development :: Libraries :: Python Modules
Classifier: Topic :: Software Development :: Libraries
Classifier: Topic :: Software Development
Classifier: Topic :: System :: Archiving :: Packaging
Classifier: Topic :: System :: Installation/Setup
Classifier: Topic :: System :: Software Distribution
Classifier: Programming Language :: Python :: 3 :: Only
Classifier: Programming Language :: Python :: 3.12
Classifier: Programming Language :: Python
Requires-Python: >=3.12
Requires-Dist: typer>=0.12.5
Requires-Dist: boto3>=1.34.0
Requires-Dist: pydantic-settings>=2.12.0
